AiPackageWrapper/__init__.py
AiPackageWrapper/data_augmentation_module.py
AiPackageWrapper/ocr_module.py
AiPackageWrapper/sentiment_analyzer_module.py
AiPackageWrapper/xai_module.py
aipackagewrapper-1.0.0.dist-info/LICENSE
aipackagewrapper-1.0.0.dist-info/METADATA
aipackagewrapper-1.0.0.dist-info/WHEEL
aipackagewrapper-1.0.0.dist-info/RECORD
